bbtm/__init__.py
bbtm/bbtm.py
bbtm-1.0.0.dist-info/METADATA
bbtm-1.0.0.dist-info/WHEEL
bbtm-1.0.0.dist-info/entry_points.txt
bbtm-1.0.0.dist-info/top_level.txt
bbtm-1.0.0.dist-info/RECORD
